tp1/modulo.v
module Notas (a,b,c,d,s0,s1,s2,,s3,s4,s5,s6,reset,ready);
  input wire a,b,c,d,reset,ready;
  output reg s0,s1,s2,s3,s4,s5,s6;

  always @ (*) begin
    if (reset) begin
      s0 = 1;
      s1 = 1;
      s2 = 1;
      s3 = 1;
      s4 = 1;
      s5 = 1;
      s6 = 1;
    end
    else if (ready) begin
        if ((a & b & c) == 0) begin
          s0 = 1;
          s1 = 1;
          s2 = 1;
          s3 = 1;
          s4 = 1;
          s5 = 1;
          s6 = 1;
        end

        s0 = ~(d | (~a & ~b & ~c));
        s1 = ~((a & ~c & d) | (~a & ~b & ~c) | (a & b & ~d) | (~a & b & c) | (~a & c & ~d));
        s2 = ~((~a & ~c) | (b & ~c) | (b & d) | (a & c & d));
        s3 = ~((~a & ~b) | (c & ~d) | (~a & ~d) | (~b & ~d));
        s4 = ~((~a & ~b) | (a & b & ~c) | (b & ~c & d) | (~b & c & ~d));
        s5 = ~((~b & d) | (~a & b & c) | (~a & ~b & ~c) | (a & ~b & c) | (a & b & ~c & ~d));
        s6 = ~((~a & ~b & ~c) | (a & ~b & ~d) | (a & b & c));

        //s0 = ((b | ~c | d) & (a | ~c | ~d) & (c | ~d));
        //s1 = ((~b | c | d) & (~a | b | ~c) & (a | c | d) & (a | ~b | ~d));
        //s2 = ((~a | ~b | c) & (c | ~d) & (a | ~b | ~c));
        //s3 = ((b | d) & (a | d) & (a | b | ~c));
        //s4 = ((b | c) & (~a | b | ~d) & (a | c | d) & (a | ~b | ~c));
        //s5 = ((~a | ~b | c | ~d) & (~a | b | ~c) & (a | b | d) & (a | b | c) & (a | ~b | ~c | ~d));
        //s6 = ((b) & (~a | c) & (a | d));
    end
  end
endmodule // Notas

tp1/testbench.v
`include "modulo.v"

module testbench();
  reg a,b,c,d,reset,ready;
  wire s0,s1,s2,s3,s4,s5,s6;

  Notas ex_instancia1(.a(a), .b(b), .c(c), .d(d), .s0(s0), .s1(s1), .s2(s2), .s3(s3), .s4(s4), .s5(s5), .s6(s6), .reset(reset), .ready(ready));

  initial begin
    a = 0;
    b = 0;
    c = 0;
    d = 0;

    $dumpfile("ondas_xylo.vcd");
    $dumpvars(0, testbench);
    $display("a b c d = s0 s1 s2 s3 s4 s5 s6");
    $monitor("%b%b%b%b = %b %b %b %b %b %b %b ",a,b,c,d,s0,s1,s2,,s3,s4,s5,s6);


    //always @ ( * ) begin
    //  #1; clock = ~clock;
    //end

               //#1; clock = 4'b1;
               //#1; reset = 1'b1;
               //#1; reset = 1'b0;
               reset = 0;
          #1;  reset = 1;

          #1;  ready = 0;  a = 0; b =0; c = 0; d = 0; ready = 1;
          #1;  ready = 0;  a = 0; b =0; c = 0; d = 1; ready = 1;
          #1;  ready = 0;  a = 0; b =0; c = 1; d = 0; ready = 1;
          #1;  ready = 0;  a = 0; b =0; c = 1; d = 1; ready = 1;
          #1;  ready = 0;  a = 0; b =1; c = 0; d = 0; ready = 1;
          #1;  ready = 0;  a = 0; b =1; c = 0; d = 1; ready = 1;
          #1;  ready = 0;  a = 0; b =1; c = 1; d = 0; ready = 1;
          #1;  ready = 0;  a = 0; b =1; c = 1; d = 1; ready = 1;
          #1;  ready = 0;  a = 1; b =0; c = 0; d = 0; ready = 1;
          #1;  ready = 0;  a = 1; b =0; c = 0; d = 1; ready = 1;
          #1;  ready = 0;  a = 1; b =0; c = 1; d = 0; ready = 1;
          #1;  ready = 0;  a = 1; b =0; c = 1; d = 1; ready = 1;
          #1;  ready = 0;  a = 1; b =1; c = 0; d = 0; ready = 1;
          #1;  ready = 0;  a = 1; b =1; c = 0; d = 1; ready = 1;
          #1;  ready = 0;  a = 1; b =1; c = 1; d = 0; ready = 1;
          #1;  ready = 0;  a = 1; b =1; c = 1; d = 1; ready = 1;

           $finish;
  end
endmodule

tp1/ondas_xylo.vcd
$date
	Sun Sep 29 11:10:39 2019
$end
$version
	Icarus Verilog
$end
$timescale
	1s
$end
$scope module testbench $end
$var wire 1 ! s6 $end
$var wire 1 " s5 $end
$var wire 1 # s4 $end
$var wire 1 $ s3 $end
$var wire 1 % s2 $end
$var wire 1 & s1 $end
$var wire 1 ' s0 $end
$var reg 1 ( a $end
$var reg 1 ) b $end
$var reg 1 * c $end
$var reg 1 + d $end
$var reg 1 , ready $end
$var reg 1 - reset $end
$scope module ex_instancia1 $end
$var wire 1 ( a $end
$var wire 1 ) b $end
$var wire 1 * c $end
$var wire 1 + d $end
$var wire 1 , ready $end
$var wire 1 - reset $end
$var reg 1 ' s0 $end
$var reg 1 & s1 $end
$var reg 1 % s2 $end
$var reg 1 $ s3 $end
$var reg 1 # s4 $end
$var reg 1 " s5 $end
$var reg 1 ! s6 $end
$upscope $end
$upscope $end
$enddefinitions $end
#0
$dumpvars
0-
x,
0+
0*
0)
0(
x'
x&
x%
x$
x#
x"
x!
$end
#1
1!
1"
1#
1$
1%
1&
1'
1-
#2
1,
#3
1+
1,
#4
0+
1*
1,
#5
1+
1,
#6
0+
0*
1)
1,
#7
1+
1,
#8
0+
1*
1,
#9
1+
1,
#10
0+
0*
0)
1(
1,
#11
1+
1,
#12
0+
1*
1,
#13
1+
1,
#14
0+
0*
1)
1,
#15
1+
1,
#16
0+
1*
1,
#17
1+
1,
